design.sv
module fifo #(
    parameter DEPTH = 8,
    parameter WIDTH = 8,
    parameter PTR_WIDTH = $clog2(DEPTH),
    parameter COUNT_WIDTH = $clog2(DEPTH+1)
)(
    input logic clk, rst,
    input logic wr_en, rd_en,
    input logic [WIDTH-1:0] data_in,
    output logic [WIDTH-1:0] data_out,
    output logic full, empty,
    output logic [COUNT_WIDTH-1:0] count
);

    logic [WIDTH-1:0] mem [0:DEPTH-1];
    logic [PTR_WIDTH-1:0] wr_ptr, rd_ptr;
    logic write_accept, read_accept;

    assign full  = (count == DEPTH);
    assign empty = (count == 0);

    assign write_accept = wr_en && !full;
    assign read_accept  = rd_en && !empty;

    // FIFO operation
    always_ff @(posedge clk) begin
        if (rst) begin
            wr_ptr   <= 0;
            rd_ptr   <= 0;
            count    <= 0;
            data_out <= 0;
        end
        else begin
            if (write_accept) begin
                mem[wr_ptr] <= data_in;

                if (wr_ptr == DEPTH-1)
                    wr_ptr <= 0;
                else
                    wr_ptr <= wr_ptr + 1'b1;
            end

            if (read_accept) begin
                data_out <= mem[rd_ptr];

                if (rd_ptr == DEPTH-1)
                    rd_ptr <= 0;
                else
                    rd_ptr <= rd_ptr + 1'b1;
            end

            // Update FIFO count
            case ({write_accept, read_accept})
                2'b10: count <= count + 1'b1;
                2'b01: count <= count - 1'b1;
                default: count <= count;
            endcase
        end
    end

endmodule

testbench.sv
`timescale 1ns/1ps

module tb;

    parameter DEPTH = 8;
    parameter WIDTH = 8;

    logic clk, rst;
    logic wr_en, rd_en;
    logic [WIDTH-1:0] data_in, data_out;
    logic full, empty;
    logic [$clog2(DEPTH+1)-1:0] count;

    fifo #(.DEPTH(DEPTH), .WIDTH(WIDTH)) dut (
        .clk(clk),
        .rst(rst),
        .wr_en(wr_en),
        .rd_en(rd_en),
        .data_in(data_in),
        .data_out(data_out),
        .full(full),
        .empty(empty),
        .count(count)
    );

    // Clock generation
    initial clk = 0;
    always #5 clk = ~clk;

    // Fixed-size reference FIFO for the scoreboard
    logic [WIDTH-1:0] ref_mem [0:DEPTH-1];
    integer ref_head, ref_tail, ref_count;
    integer accepted_read, accepted_write;
    integer blocked_write, blocked_read;
    integer previous_count;
    integer errors;
    logic [WIDTH-1:0] expected_data;

    integer saw_write, saw_read, saw_full, saw_empty;

    // Compare the DUT with the reference FIFO after each clock edge
    always @(posedge clk) begin
        if (rst) begin
            ref_head = 0;
            ref_tail = 0;
            ref_count = 0;
        end
        else begin
            previous_count = count;
            accepted_read = rd_en && !empty;
            accepted_write = wr_en && !full;
            blocked_write = wr_en && full && !rd_en;
            blocked_read = rd_en && empty && !wr_en;

            if (wr_en) saw_write = 1;
            if (rd_en) saw_read = 1;
            if (full) saw_full = 1;
            if (empty) saw_empty = 1;

            // Save the oldest item before updating the reference FIFO
            if (accepted_read) begin
                if (ref_count == 0) begin
                    $display("ERROR: Scoreboard expected a read from an empty FIFO");
                    errors = errors + 1;
                end
                else begin
                    expected_data = ref_mem[ref_head];
                    ref_head = (ref_head + 1) % DEPTH;
                    ref_count = ref_count - 1;
                end
            end

            if (accepted_write) begin
                if (ref_count >= DEPTH) begin
                    $display("ERROR: Scoreboard expected a write to a full FIFO");
                    errors = errors + 1;
                end
                else begin
                    ref_mem[ref_tail] = data_in;
                    ref_tail = (ref_tail + 1) % DEPTH;
                    ref_count = ref_count + 1;
                end
            end

            // Wait for the DUT's nonblocking assignments to take effect
            #1;

            if (accepted_read) begin
                if (data_out !== expected_data) begin
                    $display("ERROR: DATA MISMATCH: expected=%h actual=%h",
                             expected_data, data_out);
                    errors = errors + 1;
                end
                else begin
                    $display("READ PASS: Data=%h", data_out);
                end
            end

            if (count !== ref_count) begin
                $display("ERROR: Count mismatch: expected=%0d actual=%0d",
                         ref_count, count);
                errors = errors + 1;
            end

            if (count > DEPTH) begin
                $display("ERROR: Count exceeded FIFO depth");
                errors = errors + 1;
            end

            if (blocked_write && count !== previous_count) begin
                $display("ERROR: FIFO count changed during blocked overflow write");
                errors = errors + 1;
            end

            if (blocked_read && count !== previous_count) begin
                $display("ERROR: FIFO count changed during blocked underflow read");
                errors = errors + 1;
            end
        end
    end

    task automatic write_data(input logic [WIDTH-1:0] data);
        begin
            @(negedge clk);
            wr_en = 1;
            rd_en = 0;
            data_in = data;

            @(negedge clk);
            wr_en = 0;
        end
    endtask

    task automatic read_data;
        begin
            @(negedge clk);
            wr_en = 0;
            rd_en = 1;

            @(negedge clk);
            rd_en = 0;
        end
    endtask

    task automatic simultaneous_rw(input logic [WIDTH-1:0] data);
        begin
            @(negedge clk);
            wr_en = 1;
            rd_en = 1;
            data_in = data;

            @(negedge clk);
            wr_en = 0;
            rd_en = 0;
        end
    endtask

    integer i;

    initial begin
        rst = 1;
        wr_en = 0;
        rd_en = 0;
        data_in = 0;

        ref_head = 0;
        ref_tail = 0;
        ref_count = 0;
        errors = 0;
        saw_write = 0;
        saw_read = 0;
        saw_full = 0;
        saw_empty = 0;

        $dumpfile("dump.vcd");
        $dumpvars(0, tb);

        $display("FIFO VERIFICATION STARTED");

        repeat (2) @(negedge clk);
        rst = 0;

        $display("TEST 1: Normal write/read");
        write_data(8'h24);
        write_data(8'h81);
        write_data(8'h09);
        write_data(8'h63);

        repeat (2) @(negedge clk);

        read_data();
        read_data();
        read_data();
        read_data();

        $display("TEST 2: Simultaneous read/write");
        write_data(8'hA1);
        write_data(8'hB2);
        simultaneous_rw(8'hC3);

        read_data();
        read_data();

        $display("TEST 3: Fill FIFO");
        for (i = 0; i < DEPTH; i = i + 1)
            write_data(8'h40 + i);

        repeat (2) @(negedge clk);

        if (full)
            $display("PASS: FIFO is full");
        else begin
            $display("ERROR: FIFO did not become full");
            errors = errors + 1;
        end

        $display("TEST 4: Overflow protection");
        @(negedge clk);
        wr_en = 1;
        rd_en = 0;
        data_in = 8'hEE;

        @(negedge clk);
        wr_en = 0;

        $display("TEST 5: Empty the FIFO");
        for (i = 0; i < DEPTH; i = i + 1)
            read_data();

        repeat (2) @(negedge clk);

        if (empty)
            $display("PASS: FIFO is empty");
        else begin
            $display("ERROR: FIFO did not become empty");
            errors = errors + 1;
        end

        $display("TEST 6: Underflow protection");
        @(negedge clk);
        wr_en = 0;
        rd_en = 1;

        @(negedge clk);
        rd_en = 0;

        repeat (2) @(negedge clk);

        $display("Final count = %0d", count);
        $display("Observed write=%0d read=%0d full=%0d empty=%0d",
                 saw_write, saw_read, saw_full, saw_empty);

        if (errors == 0)
            $display("RESULT: ALL CHECKS PASSED");
        else
            $display("RESULT: %0d CHECK(S) FAILED", errors);

        $display("FIFO VERIFICATION COMPLETED");
        $finish;
    end

endmodule

dump.vcd
$date
	Wed Sep 30 00:36:22 2026
$end
$version
	Icarus Verilog
$end
$timescale
	1ps
$end
$scope module tb $end
$var wire 1 ! full $end
$var wire 1 " empty $end
$var wire 8 # data_out [7:0] $end
$var wire 4 $ count [3:0] $end
$var parameter 32 % DEPTH $end
$var parameter 32 & WIDTH $end
$var reg 1 ' clk $end
$var reg 8 ( data_in [7:0] $end
$var reg 8 ) expected_data [7:0] $end
$var reg 1 * rd_en $end
$var reg 1 + rst $end
$var reg 1 , wr_en $end
$var integer 32 - accepted_read [31:0] $end
$var integer 32 . accepted_write [31:0] $end
$var integer 32 / blocked_read [31:0] $end
$var integer 32 0 blocked_write [31:0] $end
$var integer 32 1 errors [31:0] $end
$var integer 32 2 i [31:0] $end
$var integer 32 3 previous_count [31:0] $end
$var integer 32 4 ref_count [31:0] $end
$var integer 32 5 ref_head [31:0] $end
$var integer 32 6 ref_tail [31:0] $end
$var integer 32 7 saw_empty [31:0] $end
$var integer 32 8 saw_full [31:0] $end
$var integer 32 9 saw_read [31:0] $end
$var integer 32 : saw_write [31:0] $end
$scope module dut $end
$var wire 1 ' clk $end
$var wire 8 ; data_in [7:0] $end
$var wire 1 * rd_en $end
$var wire 1 < read_accept $end
$var wire 1 + rst $end
$var wire 1 , wr_en $end
$var wire 1 = write_accept $end
$var wire 1 ! full $end
$var wire 1 " empty $end
$var parameter 32 > COUNT_WIDTH $end
$var parameter 32 ? DEPTH $end
$var parameter 32 @ PTR_WIDTH $end
$var parameter 32 A WIDTH $end
$var reg 4 B count [3:0] $end
$var reg 8 C data_out [7:0] $end
$var reg 3 D rd_ptr [2:0] $end
$var reg 3 E wr_ptr [2:0] $end
$upscope $end
$scope task read_data $end
$upscope $end
$scope task simultaneous_rw $end
$upscope $end
$scope task write_data $end
$upscope $end
$upscope $end
$enddefinitions $end
$comment Show the parameter values. $end
$dumpall
b1000 A
b11 @
b1000 ?
b100 >
b1000 &
b1000 %
$end
#0
$dumpvars
bx E
bx D
bx C
bx B
0=
0<
b0 ;
b0 :
b0 9
b0 8
b0 7
b0 6
b0 5
b0 4
bx 3
bx 2
b0 1
bx 0
bx /
bx .
bx -
0,
1+
0*
bx )
b0 (
0'
bx $
bx #
x"
x!
$end
#5000
b0 #
b0 C
0!
1"
b0 $
b0 B
b0 D
b0 E
1'
#10000
0'
#15000
1'
#20000
0+
0'
#25000
b1 7
b0 /
b0 0
b0 .
b0 -
b0 3
1'
#30000
1=
b100100 (
b100100 ;
1,
0'
#35000
0"
b1 $
b1 B
b1 E
b1 4
b1 6
b1 :
b1 .
1'
#40000
0=
0,
0'
#45000
b0 .
b1 3
1'
#50000
1=
b10000001 (
b10000001 ;
1,
0'
#55000
b10 $
b10 B
b10 E
b10 4
b10 6
b1 .
1'
#60000
0=
0,
0'
#65000
b0 .
b10 3
1'
#70000
1=
b1001 (
b1001 ;
1,
0'
#75000
b11 $
b11 B
b11 E
b11 4
b11 6
b1 .
1'
#80000
0=
0,
0'
#85000
b0 .
b11 3
1'
#90000
1=
b1100011 (
b1100011 ;
1,
0'
#95000
b100 $
b100 B
b100 E
b100 4
b100 6
b1 .
1'
#100000
0=
0,
0'
#105000
b0 .
b100 3
1'
#110000
0'
#115000
1'
#120000
0'
#125000
1'
#130000
1<
1*
0'
#135000
b11 $
b11 B
b1 D
b100100 #
b100100 C
b11 4
b1 5
b100100 )
b1 9
b1 -
1'
#140000
0<
0*
0'
#145000
b0 -
b11 3
1'
#150000
1<
1*
0'
#155000
b10 $
b10 B
b10 D
b10000001 #
b10000001 C
b10 4
b10 5
b10000001 )
b1 -
1'
#160000
0<
0*
0'
#165000
b0 -
b10 3
1'
#170000
1<
1*
0'
#175000
b1 $
b1 B
b11 D
b1001 #
b1001 C
b1 4
b11 5
b1001 )
b1 -
1'
#180000
0<
0*
0'
#185000
b0 -
b1 3
1'
#190000
1<
1*
0'
#195000
0<
1"
b0 $
b0 B
b100 D
b1100011 #
b1100011 C
b0 4
b100 5
b1100011 )
b1 -
1'
#200000
0*
0'
#205000
b0 -
b0 3
1'
#210000
1=
b10100001 (
b10100001 ;
1,
0'
#215000
0"
b1 $
b1 B
b101 E
b1 4
b101 6
b1 .
1'
#220000
0=
0,
0'
#225000
b0 .
b1 3
1'
#230000
1=
b10110010 (
b10110010 ;
1,
0'
#235000
b10 $
b10 B
b110 E
b10 4
b110 6
b1 .
1'
#240000
0=
0,
0'
#245000
b0 .
b10 3
1'
#250000
1<
1=
b11000011 (
b11000011 ;
1*
1,
0'
#255000
b101 D
b10100001 #
b10100001 C
b111 E
b111 6
b10 4
b101 5
b10100001 )
b1 .
b1 -
1'
#260000
0<
0=
0*
0,
0'
#265000
b0 .
b0 -
1'
#270000
1<
1*
0'
#275000
b1 $
b1 B
b110 D
b10110010 #
b10110010 C
b1 4
b110 5
b10110010 )
b1 -
1'
#280000
0<
0*
0'
#285000
b0 -
b1 3
1'
#290000
1<
1*
0'
#295000
0<
1"
b0 $
b0 B
b111 D
b11000011 #
b11000011 C
b0 4
b111 5
b11000011 )
b1 -
1'
#300000
b0 2
0*
0'
#305000
b0 -
b0 3
1'
#310000
1=
b1000000 (
b1000000 ;
1,
0'
#315000
0"
b1 $
b1 B
b0 E
b1 4
b0 6
b1 .
1'
#320000
0=
b1 2
0,
0'
#325000
b0 .
b1 3
1'
#330000
1=
b1000001 (
b1000001 ;
1,
0'
#335000
b10 $
b10 B
b1 E
b10 4
b1 6
b1 .
1'
#340000
0=
b10 2
0,
0'
#345000
b0 .
b10 3
1'
#350000
1=
b1000010 (
b1000010 ;
1,
0'
#355000
b11 $
b11 B
b10 E
b11 4
b10 6
b1 .
1'
#360000
0=
b11 2
0,
0'
#365000
b0 .
b11 3
1'
#370000
1=
b1000011 (
b1000011 ;
1,
0'
#375000
b100 $
b100 B
b11 E
b100 4
b11 6
b1 .
1'
#380000
0=
b100 2
0,
0'
#385000
b0 .
b100 3
1'
#390000
1=
b1000100 (
b1000100 ;
1,
0'
#395000
b101 $
b101 B
b100 E
b101 4
b100 6
b1 .
1'
#400000
0=
b101 2
0,
0'
#405000
b0 .
b101 3
1'
#410000
1=
b1000101 (
b1000101 ;
1,
0'
#415000
b110 $
b110 B
b101 E
b110 4
b101 6
b1 .
1'
#420000
0=
b110 2
0,
0'
#425000
b0 .
b110 3
1'
#430000
1=
b1000110 (
b1000110 ;
1,
0'
#435000
b111 $
b111 B
b110 E
b111 4
b110 6
b1 .
1'
#440000
0=
b111 2
0,
0'
#445000
b0 .
b111 3
1'
#450000
1=
b1000111 (
b1000111 ;
1,
0'
#455000
0=
1!
b1000 $
b1000 B
b111 E
b1000 4
b111 6
b1 .
1'
#460000
b1000 2
0,
0'
#465000
b1 8
b0 .
b1000 3
1'
#470000
0'
#475000
1'
#480000
0'
#485000
1'
#490000
b11101110 (
b11101110 ;
1,
0'
#495000
b1 0
1'
#500000
b0 2
0,
0'
#505000
b0 0
1'
#510000
1<
1*
0'
#515000
0!
b111 $
b111 B
b0 D
b1000000 #
b1000000 C
b111 4
b0 5
b1000000 )
b1 -
1'
#520000
0<
b1 2
0*
0'
#525000
b0 -
b111 3
1'
#530000
1<
1*
0'
#535000
b110 $
b110 B
b1 D
b1000001 #
b1000001 C
b110 4
b1 5
b1000001 )
b1 -
1'
#540000
0<
b10 2
0*
0'
#545000
b0 -
b110 3
1'
#550000
1<
1*
0'
#555000
b101 $
b101 B
b10 D
b1000010 #
b1000010 C
b101 4
b10 5
b1000010 )
b1 -
1'
#560000
0<
b11 2
0*
0'
#565000
b0 -
b101 3
1'
#570000
1<
1*
0'
#575000
b100 $
b100 B
b11 D
b1000011 #
b1000011 C
b100 4
b11 5
b1000011 )
b1 -
1'
#580000
0<
b100 2
0*
0'
#585000
b0 -
b100 3
1'
#590000
1<
1*
0'
#595000
b11 $
b11 B
b100 D
b1000100 #
b1000100 C
b11 4
b100 5
b1000100 )
b1 -
1'
#600000
0<
b101 2
0*
0'
#605000
b0 -
b11 3
1'
#610000
1<
1*
0'
#615000
b10 $
b10 B
b101 D
b1000101 #
b1000101 C
b10 4
b101 5
b1000101 )
b1 -
1'
#620000
0<
b110 2
0*
0'
#625000
b0 -
b10 3
1'
#630000
1<
1*
0'
#635000
b1 $
b1 B
b110 D
b1000110 #
b1000110 C
b1 4
b110 5
b1000110 )
b1 -
1'
#640000
0<
b111 2
0*
0'
#645000
b0 -
b1 3
1'
#650000
1<
1*
0'
#655000
0<
1"
b0 $
b0 B
b111 D
b1000111 #
b1000111 C
b0 4
b111 5
b1000111 )
b1 -
1'
#660000
b1000 2
0*
0'
#665000
b0 -
b0 3
1'
#670000
0'
#675000
1'
#680000
0'
#685000
1'
#690000
1*
0'
#695000
b1 /
1'
#700000
0*
0'
#705000
b0 /
1'
